{
  "observation_id": "obs_f6e41fbc",
  "timestamp": "2026-04-07T06:19:24.064970",
  "screenshot_path": "exploration/20260407-055959-1c92/step_021.png",
  "ui_structure_path": null,
  "screen_purpose": "This screen is for booking hotels as part of a travel booking process.",
  "screen_type": "form",
  "app_state": {
    "logged_in": "yes"
  },
  "elements": [
    {
      "element_id": "elem_01",
      "reference": {
        "resource_id": null,
        "text": "Hotel Name",
        "content_description": null,
        "class_name": null,
        "bounds": null,
        "description": "top-left"
      },
      "element_type": "text_field",
      "semantic_role": "Allows user to enter hotel name or location",
      "label": "Hotel Name",
      "is_interactive": true,
      "is_enabled": true,
      "is_selected": false,
      "possible_actions": [
        "type"
      ],
      "inferred_destination": "hotels_search_results",
      "confidence": 0.95
    },
    {
      "element_id": "elem_02",
      "reference": {
        "resource_id": null,
        "text": "Check-in Date",
        "content_description": null,
        "class_name": null,
        "bounds": null,
        "description": "top-right"
      },
      "element_type": "text_field",
      "semantic_role": "Allows user to enter check-in date",
      "label": "Check-in Date",
      "is_interactive": true,
      "is_enabled": true,
      "is_selected": false,
      "possible_actions": [
        "type"
      ],
      "inferred_destination": "date_picker",
      "confidence": 0.95
    },
    {
      "element_id": "elem_03",
      "reference": {
        "resource_id": null,
        "text": "Check-out Date",
        "content_description": null,
        "class_name": null,
        "bounds": null,
        "description": "bottom-left"
      },
      "element_type": "text_field",
      "semantic_role": "Allows user to enter check-out date",
      "label": "Check-out Date",
      "is_interactive": true,
      "is_enabled": true,
      "is_selected": false,
      "possible_actions": [
        "type"
      ],
      "inferred_destination": "date_picker",
      "confidence": 0.95
    },
    {
      "element_id": "elem_04",
      "reference": {
        "resource_id": null,
        "text": "Guests",
        "content_description": null,
        "class_name": null,
        "bounds": null,
        "description": "bottom-right"
      },
      "element_type": "dropdown",
      "semantic_role": "Allows user to select number of guests",
      "label": "Guests",
      "is_interactive": true,
      "is_enabled": true,
      "is_selected": false,
      "possible_actions": [
        "type"
      ],
      "inferred_destination": "guest_selection",
      "confidence": 0.95
    }
  ],
  "navigation_context": {
    "arrived_from": null,
    "arrival_action": null,
    "visible_navigation": [
      "Hotels",
      "Sight Seeing"
    ],
    "active_navigation": "Hotels",
    "back_available": true,
    "inferred_depth": 0
  },
  "confidence": 0.9,
  "raw_ai_response": "{\n  \"screen_purpose\": \"This screen is for booking hotels as part of a travel booking process.\",\n  \"screen_type\": \"form\",\n  \"app_state\": {\n    \"logged_in\": \"yes\"\n  },\n  \"elements\": [\n    {\n      \"element_id\": \"elem_01\",\n      \"element_type\": \"text_field\",\n      \"semantic_role\": \"Allows user to enter hotel name or location\",\n      \"label\": \"Hotel Name\",\n      \"is_interactive\": true,\n      \"is_enabled\": true,\n      \"is_selected\": false,\n      \"possible_actions\": [\"type\"],\n      \"inferred_destination\": \"hotels_search_results\",\n      \"bounds_description\": \"top-left\",\n      \"confidence\": 0.95\n    },\n    {\n      \"element_id\": \"elem_02\",\n      \"element_type\": \"text_field\",\n      \"semantic_role\": \"Allows user to enter check-in date\",\n      \"label\": \"Check-in Date\",\n      \"is_interactive\": true,\n      \"is_enabled\": true,\n      \"is_selected\": false,\n      \"possible_actions\": [\"type\"],\n      \"inferred_destination\": \"date_picker\",\n      \"bounds_description\": \"top-right\",\n      \"confidence\": 0.95\n    },\n    {\n      \"element_id\": \"elem_03\",\n      \"element_type\": \"text_field\",\n      \"semantic_role\": \"Allows user to enter check-out date\",\n      \"label\": \"Check-out Date\",\n      \"is_interactive\": true,\n      \"is_enabled\": true,\n      \"is_selected\": false,\n      \"possible_actions\": [\"type\"],\n      \"inferred_destination\": \"date_picker\",\n      \"bounds_description\": \"bottom-left\",\n      \"confidence\": 0.95\n    },\n    {\n      \"element_id\": \"elem_04\",\n      \"element_type\": \"dropdown\",\n      \"semantic_role\": \"Allows user to select number of guests\",\n      \"label\": \"Guests\",\n      \"is_interactive\": true,\n      \"is_enabled\": true,\n      \"is_selected\": false,\n      \"possible_actions\": [\"type\"],\n      \"inferred_destination\": \"guest_selection\",\n      \"bounds_description\": \"bottom-right\",\n      \"confidence\": 0.95\n    }\n  ],\n  \"navigation_context\": {\n    \"visible_navigation\": [\"Hotels\", \"Sight Seeing\"],\n    \"active_navigation\": \"Hotels\",\n    \"back_available\": true,\n    \"inferred_depth\": 0\n  },\n  \"confidence\": 0.9\n}"
}